[
  {
    "Trustee": "MS Firm",
    "Sale_date": "10/2/2025",
    "Sale_time": "10:15 AM",
    "FileNo": "223390.100225.447680 FC",
    "PropAddress": "",
    "PropCity": "",
    "PropZip": "",
    "County": "Jackson County",
    "OpeningBid": "36757.94",
    "vendor": "",
    "status- DROP DOWN": "",
    "Foreclosure Status": ""
  },
  {
    "Trustee": "MS Firm",
    "Sale_date": "10/3/2025",
    "Sale_time": "9:00 AM",
    "FileNo": "228208.100325.461207 FC",
    "PropAddress": "",
    "PropCity": "",
    "PropZip": "",
    "County": "St. Louis County",
    "OpeningBid": "20233.74",
    "vendor": "",
    "status- DROP DOWN": "",
    "Foreclosure Status": ""
  },
  {
    "Trustee": "MS Firm",
    "Sale_date": "10/6/2025",
    "Sale_time": "9:00 AM",
    "FileNo": "226684.100625.455241 FC",
    "PropAddress": "",
    "PropCity": "",
    "PropZip": "",
    "County": "St. Louis City",
    "OpeningBid": "0.00",
    "vendor": "Auction.com",
    "status- DROP DOWN": "",
    "Foreclosure Status": ""
  },
  {
    "Trustee": "MS Firm",
    "Sale_date": "10/6/2025",
    "Sale_time": "9:00 AM",
    "FileNo": "228066.100625.461599 FC",
    "PropAddress": "",
    "PropCity": "",
    "PropZip": "",
    "County": "St. Louis City",
    "OpeningBid": "0.00",
    "vendor": "Auction.com",
    "status- DROP DOWN": "",
    "Foreclosure Status": ""
  },
  {
    "Trustee": "MS Firm",
    "Sale_date": "10/6/2025",
    "Sale_time": "9:00 AM",
    "FileNo": "77989.100625.461449 FC",
    "PropAddress": "",
    "PropCity": "",
    "PropZip": "",
    "County": "St. Louis City",
    "OpeningBid": "67243.86",
    "vendor": "",
    "status- DROP DOWN": "",
    "Foreclosure Status": ""
  },
  {
    "Trustee": "MS Firm",
    "Sale_date": "10/6/2025",
    "Sale_time": "4:00 PM",
    "FileNo": "225753.100625.453447 FC",
    "PropAddress": "",
    "PropCity": "",
    "PropZip": "",
    "County": "Jackson County",
    "OpeningBid": "95992.73",
    "vendor": "",
    "status- DROP DOWN": "",
    "Foreclosure Status": ""
  },
  {
    "Trustee": "MS Firm",
    "Sale_date": "10/7/2025",
    "Sale_time": "9:00 AM",
    "FileNo": "226671.100725.455214 FC",
    "PropAddress": "",
    "PropCity": "",
    "PropZip": "",
    "County": "St. Charles County",
    "OpeningBid": "0.00",
    "vendor": "ServiceLink - Hudson",
    "status- DROP DOWN": "",
    "Foreclosure Status": ""
  },
  {
    "Trustee": "MS Firm",
    "Sale_date": "10/7/2025",
    "Sale_time": "2:00 PM",
    "FileNo": "225118.100725.461152 FC",
    "PropAddress": "",
    "PropCity": "",
    "PropZip": "",
    "County": "St. Louis County",
    "OpeningBid": "121000.00",
    "vendor": "",
    "status- DROP DOWN": "",
    "Foreclosure Status": ""
  },
  {
    "Trustee": "MS Firm",
    "Sale_date": "10/7/2025",
    "Sale_time": "2:00 PM",
    "FileNo": "225120.100725.461151 FC",
    "PropAddress": "",
    "PropCity": "",
    "PropZip": "",
    "County": "St. Louis County",
    "OpeningBid": "105000.00",
    "vendor": "",
    "status- DROP DOWN": "",
    "Foreclosure Status": ""
  },
  {
    "Trustee": "MS Firm",
    "Sale_date": "10/8/2025",
    "Sale_time": "9:00 AM",
    "FileNo": "222390.446110 JFC",
    "PropAddress": "",
    "PropCity": "",
    "PropZip": "",
    "County": "St. Louis City",
    "OpeningBid": "61200.00",
    "vendor": "Auction.com",
    "status- DROP DOWN": "",
    "Foreclosure Status": ""
  },
  {
    "Trustee": "MS Firm",
    "Sale_date": "10/9/2025",
    "Sale_time": "9:00 AM",
    "FileNo": "224029.100925.461508 FC",
    "PropAddress": "",
    "PropCity": "",
    "PropZip": "",
    "County": "Jefferson County",
    "OpeningBid": "0.00",
    "vendor": "Auction.com",
    "status- DROP DOWN": "",
    "Foreclosure Status": ""
  },
  {
    "Trustee": "MS Firm",
    "Sale_date": "10/10/2025",
    "Sale_time": "9:00 AM",
    "FileNo": "214275.101025.462170 FC",
    "PropAddress": "",
    "PropCity": "",
    "PropZip": "",
    "County": "St. Louis County",
    "OpeningBid": "",
    "vendor": "",
    "status- DROP DOWN": "",
    "Foreclosure Status": ""
  },
  {
    "Trustee": "MS Firm",
    "Sale_date": "10/10/2025",
    "Sale_time": "9:00 AM",
    "FileNo": "217003.101025.456016 FC",
    "PropAddress": "",
    "PropCity": "",
    "PropZip": "",
    "County": "St. Louis County",
    "OpeningBid": "0.00",
    "vendor": "Auction.com",
    "status- DROP DOWN": "",
    "Foreclosure Status": ""
  },
  {
    "Trustee": "MS Firm",
    "Sale_date": "10/10/2025",
    "Sale_time": "9:00 AM",
    "FileNo": "225928.101025.453774 FC",
    "PropAddress": "",
    "PropCity": "",
    "PropZip": "",
    "County": "St. Louis County",
    "OpeningBid": "0.00",
    "vendor": "",
    "status- DROP DOWN": "",
    "Foreclosure Status": ""
  },
  {
    "Trustee": "MS Firm",
    "Sale_date": "10/10/2025",
    "Sale_time": "9:00 AM",
    "FileNo": "227116.101025.456044 FC",
    "PropAddress": "",
    "PropCity": "",
    "PropZip": "",
    "County": "St. Louis County",
    "OpeningBid": "0.00",
    "vendor": "",
    "status- DROP DOWN": "",
    "Foreclosure Status": ""
  },
  {
    "Trustee": "MS Firm",
    "Sale_date": "10/16/2025",
    "Sale_time": "9:00 AM",
    "FileNo": "198556.101625.461320 FC",
    "PropAddress": "",
    "PropCity": "",
    "PropZip": "",
    "County": "Jackson County",
    "OpeningBid": "0.00",
    "vendor": "Auction.com",
    "status- DROP DOWN": "",
    "Foreclosure Status": ""
  },
  {
    "Trustee": "MS Firm",
    "Sale_date": "10/16/2025",
    "Sale_time": "9:00 AM",
    "FileNo": "228567.101625.462202 FC",
    "PropAddress": "",
    "PropCity": "",
    "PropZip": "",
    "County": "Jackson County",
    "OpeningBid": "0.00",
    "vendor": "Auction.com",
    "status- DROP DOWN": "",
    "Foreclosure Status": ""
  },
  {
    "Trustee": "MS Firm",
    "Sale_date": "10/16/2025",
    "Sale_time": "9:00 AM",
    "FileNo": "216508.101625.461737 FC",
    "PropAddress": "",
    "PropCity": "",
    "PropZip": "",
    "County": "Jefferson County",
    "OpeningBid": "0.00",
    "vendor": "",
    "status- DROP DOWN": "",
    "Foreclosure Status": ""
  },
  {
    "Trustee": "MS Firm",
    "Sale_date": "10/16/2025",
    "Sale_time": "10:15 AM",
    "FileNo": "229418.101625.461549 FC",
    "PropAddress": "",
    "PropCity": "",
    "PropZip": "",
    "County": "Jackson County",
    "OpeningBid": "0.00",
    "vendor": "Auction.com",
    "status- DROP DOWN": "",
    "Foreclosure Status": ""
  },
  {
    "Trustee": "MS Firm",
    "Sale_date": "10/16/2025",
    "Sale_time": "3:00 PM",
    "FileNo": "206453.101625.462179 FC",
    "PropAddress": "",
    "PropCity": "",
    "PropZip": "",
    "County": "St. Louis City",
    "OpeningBid": "0.00",
    "vendor": "",
    "status- DROP DOWN": "",
    "Foreclosure Status": "",
    "continued_date": "10/27/2025"
  },
  {
    "Trustee": "MS Firm",
    "Sale_date": "10/16/2025",
    "Sale_time": "3:00 PM",
    "FileNo": "224977.101625.459651 FC",
    "PropAddress": "",
    "PropCity": "",
    "PropZip": "",
    "County": "St. Louis City",
    "OpeningBid": "0.00",
    "vendor": "Auction.com",
    "status- DROP DOWN": "",
    "Foreclosure Status": ""
  },
  {
    "Trustee": "MS Firm",
    "Sale_date": "10/10/2025",
    "Sale_time": "1:00 PM",
    "FileNo": "207979.419151 KYFC",
    "PropAddress": "",
    "PropCity": "",
    "PropZip": "",
    "County": "Jefferson County",
    "OpeningBid": "0.00",
    "vendor": "Auction.com",
    "status- DROP DOWN": "",
    "Foreclosure Status": ""
  },
  {
    "Trustee": "MS Firm",
    "Sale_date": "10/10/2025",
    "Sale_time": "1:00 PM",
    "FileNo": "216068.450796 KYFC",
    "PropAddress": "",
    "PropCity": "",
    "PropZip": "",
    "County": "Jefferson County",
    "OpeningBid": "0.00",
    "vendor": "Auction.com",
    "status- DROP DOWN": "",
    "Foreclosure Status": ""
  }
]